honeycomb_cleaner/__init__.py
honeycomb_cleaner/client.py
honeycomb_cleaner/main.py
honeycomb_cleaner-0.2.dist-info/WHEEL
honeycomb_cleaner-0.2.dist-info/entry_points.txt
honeycomb_cleaner-0.2.dist-info/METADATA
honeycomb_cleaner-0.2.dist-info/RECORD
