Metadata-Version: 2.3
Name: honeycomb-cleaner
Version: 0.2
Summary: Clean up inactive datasets and columns in Honeycomb
Author: Martín Gaitán
Author-email: Martín Gaitán <gaitan@gmail.com>
License: Apache-2.0
Requires-Dist: requests>=2.31.0
Requires-Dist: rich>=13.0.0
Requires-Python: >=3.12
Project-URL: CI, https://github.com/mgaitan/honeycomb-cleaner/actions/workflows/ci.yml
Project-URL: Changelog, https://github.com/mgaitan/honeycomb-cleaner/releases
Project-URL: Homepage, https://github.com/mgaitan/honeycomb-cleaner
Project-URL: Issues, https://github.com/mgaitan/honeycomb-cleaner/issues
